{"cameraMode":{"drawMode":0,"name":"Shaded","section":"Shading Mode"},"sceneLighting":false,"audioPlay":false,"sceneViewState":{"showFog":true,"showMaterialUpdate":false,"showSkybox":false,"showFlares":true,"showImageEffects":true,"showParticleSystems":true},"in2DMode":false,"pivot":{"x":3.069854497909546,"y":1.0856292247772217,"z":-19.918455123901368},"rotation":{"x":0.0051610106602311138,"y":0.9888578653335571,"z":0.03530693054199219,"w":-0.14459799230098725},"size":2.2113723754882814,"orthographic":false}